mms_nirs/BRUNO/__init__.py
mms_nirs/BRUNO/boundaries.py
mms_nirs/BRUNO/calc_values.py
mms_nirs/BRUNO/derivative_fit.py
mms_nirs/BRUNO/fminsearchbnd.py
mms_nirs/BRUNO/model_types.py
mms_nirs/UCLN/DefaultValues.py
mms_nirs/UCLN/UCLN.py
mms_nirs/UCLN/__init__.py
mms_nirs/UCLN/defaults.csv
mms_nirs/__init__.py
mms_nirs/utils/__init__.py
mms_nirs/utils/attenuation.py
mms_nirs/utils/dpf.py
mms_nirs/utils/extinction_coefficients.py
mms_nirs-0.4.0.dist-info/METADATA
mms_nirs-0.4.0.dist-info/WHEEL
mms_nirs-0.4.0.dist-info/RECORD
